totaltimeout.py
totaltimeout-3.0.2.dist-info/LICENSE
totaltimeout-3.0.2.dist-info/METADATA
totaltimeout-3.0.2.dist-info/WHEEL
totaltimeout-3.0.2.dist-info/top_level.txt
totaltimeout-3.0.2.dist-info/RECORD
