Metadata-Version: 2.1
Name: totaltimeout
Version: 3.0.2
Summary: Get timeouts right, without the hassle.
Home-page: https://github.com/mentalisttraceur/python-totaltimeout
Author: Alexander Kozhevnikov
Author-email: mentalisttraceur@gmail.com
License: 0BSD
Platform: UNKNOWN
Classifier: Development Status :: 5 - Production/Stable
Classifier: Programming Language :: Python :: 3
Classifier: Programming Language :: Python :: 2
Classifier: Operating System :: OS Independent
